[
    { "route": "Mawasiliano-Makumbusho", "fare": "700" },
    { "route": "Makumbusho - Mbezi Luis", "fare": "700" },
    { "route": "Mbezi Luis - Makumbusho", "fare": "700" },
    { "route": "Muhimbili - Mwenge/Makumbusho", "fare": "700" },
    { "route": "Kariakoo - Makumbusho via Kawawa Road", "fare": "700" },
    { "route": "Makumbusho - Kariakoo via Kawawa Road", "fare": "700" },
    { "route": "Kariakoo - Makumbusho via Shekilango Rd", "fare": "700" },
    { "route": "Mbweni - Tegeta", "fare": "700" },
    { "route": "Tegeta - Mbweni", "fare": "700" },
    { "route": "Tegeta - Ununio", "fare": "700" },
    { "route": "Ununio - Tegeta", "fare": "700" },
    { "route": "Mwenge/Makumbusho - Tegeta Nyuki", "fare": "700" },
    { "route": "Tegeta Nyuki - Mwenge/Makumbusho", "fare": "700" },
    { "route": "Makumbusho - Ubungo", "fare": "700" },
    { "route": "Ubungo - Makumbusho", "fare": "700" },
    { "route": "Tegeta - Ubungo", "fare": "700" },
    { "route": "Ubungo - Tegeta", "fare": "700" },
    { "route": "Makumbusho - Ubungo (Via Chuo Kikuu)", "fare": "700" },
    { "route": "Ubungo - Makumbusho (Via Chuo Kikuu)", "fare": "700" },
    { "route": "Changanyikeni - Ubungo/Mawasiliano", "fare": "700" },
    { "route": "Ubungo/Mawasiliano - Changanyikeni", "fare": "700" },
    { "route": "Makumbusho - Bunju", "fare": "700" },
    { "route": "Kariakoo - Kawe", "fare": "700" },
    { "route": "Kawe - Kariakoo", "fare": "700" },
    { "route": "Kawe - Ubungo", "fare": "700" },
    { "route": "Ubungo - Kawe", "fare": "700" },
    { "route": "Kimara Mwisho - Mwenge/Makumbusho", "fare": "700" },
    { "route": "Mwenge/Makumbusho - Kimara Mwisho", "fare": "700" },
    { "route": "Mabibo Mwisho - Makumbusho", "fare": "700" },
    { "route": "Makumbusho - Mabibo Mwisho", "fare": "700" },
    { "route": "Makumbusho - Kivukoni/Posta (via Mwanyamala)", "fare": "700" },
    { "route": "Kunduchi - Makumbusho", "fare": "700" },
    { "route": "Makumbusho - Kunduchi", "fare": "700" },
    { "route": "Makongo Juu - Makumbusho", "fare": "700" },
    { "route": "Makumbusho - Makongo Juu", "fare": "700" },
    { "route": "Makumbusho (via Ali hassan mwinyi) - Posta", "fare": "700" },
    { "route": "Posta (via Ali hassan mwinyi) - Makumbusho", "fare": "700" },
    { "route": "Makumbusho - Stesheni", "fare": "700" },
    { "route": "Kinondoni Municipal", "fare": "700" },
    { "route": "Ununio - Makumbusho", "fare": "700" },
    { "route": "Masaki - Ubungo", "fare": "700" },
    { "route": "Kawe - Mbezi Luis", "fare": "700" },
    { "route": "Mbezi Luis - Kawe", "fare": "700" },
    { "route": "Machimbo - Buguruni", "fare": "700" },
    { "route": "Buguruni - Mbagala Rangi 3", "fare": "700" },
    { "route": "Mbagala Rangi 3 - Buguruni", "fare": "700" },
    { "route": "Buza - Tandika", "fare": "700" },
    { "route": "Tandika - Buza", "fare": "700" },
    { "route": "Charambe - Temeke", "fare": "700" },
    { "route": "Temeke - Charambe", "fare": "700" },
    { "route": "Mbagala Kuu - Temeke", "fare": "700" },
    { "route": "Temeke - Mbagala Kuu", "fare": "700" },
    { "route": "Mtoni Kijichi - Temeke", "fare": "700" },
    { "route": "Temeke - Mtoni Kijichi", "fare": "700" },
    { "route": "Nzasa - Temeke", "fare": "700" },
    { "route": "Temeke - Nzasa", "fare": "700" },
    { "route": "Kiburugwa - Mbagala Zakhem", "fare": "700" },
    { "route": "Mbagala Zakhem - Kiburugwa", "fare": "700" },
    { "route": "Kilungule - Mbagala Rangi 3", "fare": "700" },
    { "route": "Mbagala Rangi 3 - Kilungule", "fare": "700" },
    { "route": "Kwa Mnyani - Mbagala Zakhem", "fare": "700" },
    { "route": "Mbagala Zakhem - Kwa Mnyani", "fare": "700" },
    { "route": "Charambe - Mbagala Rangi 3", "fare": "700" },
    { "route": "Mbagala Rangi 3 - Charambe", "fare": "700" },
    { "route": "Mbagala Rangi 3 - Mbande", "fare": "700" },
    { "route": "Mbande - Mbagala Rangi 3", "fare": "700" },
    { "route": "Mbagala Rangi 3 - Temeke", "fare": "700" },
    { "route": "Temeke - Mbagala Rangi 3", "fare": "700" },
    { "route": "Kichemchemu - Mbagala Zakhem", "fare": "700" },
    { "route": "Mbagala Zakhem - Kichemchemu", "fare": "700" },
    { "route": "Mbagala Zakhem - Mbagala Kuu", "fare": "700" },
    { "route": "Mbande - Mtoni Mtongani", "fare": "700" },
    { "route": "Mtoni Mtongani - Mbande", "fare": "700" },
    { "route": "Buguruni-Manzese", "fare": "700" },
    { "route": "Banana - Kibeberu", "fare": "700" },
    { "route": "Kibeberu - Banana", "fare": "700" },
    { "route": "Buguruni - Kivukoni/Mnazi Mmoja", "fare": "700" },
    { "route": "Kivukoni/Mnazi Mmoja - Buguruni", "fare": "700" },
    { "route": "Mnazi Mmoja - Mnyamani", "fare": "700" },
    { "route": "Mnyamani - Mnazi Mmoja", "fare": "700" },
    { "route": "Buguruni - Machimbo", "fare": "700" },
    { "route": "Buguruni/Gongo la Mboto - Pugu Kajiungeni", "fare": "700" },
    { "route": "Pugu Kajiungeni - Buguruni/Gongo la Mboto", "fare": "700" },
    { "route": "Pugu Kwalala - Shule Ya Uhuru/Gongo la Mboto", "fare": "700" },
    { "route": "Shule Ya Uhuru/Gongo la Mboto - Pugu Kwalala", "fare": "700" },
    { "route": "Buguruni - Pugu Kajiungeni", "fare": "700" },
    { "route": "Pugu Kajiungeni - Buguruni", "fare": "700" },
    { "route": "Mnazi Mmoja - Tabata Chang'Ombe (Barakuda)", "fare": "700" },
    { "route": "Tabata Chang'Ombe (Barakuda) - Mnazi Mmoja", "fare": "700" },
    { "route": "Buguruni - Tabata Chang'ombe/(Barakuda)", "fare": "700" },
    { "route": "Tabata Chang'ombe/(Barakuda) - Buguruni", "fare": "700" },
    { "route": "Tabata Chang'Ombe/(Barakuda) - Vingunguti (Via Bakhresa)", "fare": "700" },
    { "route": "Vingunguti (Via Bakhresa) - Tabata Chang'Ombe/(Barakuda)", "fare": "700" },
    { "route": "Buguruni - Tabata Kimanga", "fare": "700" },
    { "route": "Tabata Kimanga - Buguruni", "fare": "700" },
    { "route": "Tabata Kimanga - Kivukoni/Mnazi Mmoja", "fare": "700" },
    { "route": "Mnazi Mmoja - Tabata Kimanga", "fare": "700" },
    { "route": "Tabata Kimanga - Temeke", "fare": "700" },
    { "route": "Temeke - Tabata Kimanga", "fare": "700" },
    { "route": "Buguruni - Tabata Kinyerezi", "fare": "700" },
    { "route": "Tabata Kinyerezi - Buguruni", "fare": "700" },
    { "route": "Majumba Sita - Tabata Kinyerezi", "fare": "700" },
    { "route": "Bonyokwa - Tabata Segerea", "fare": "700" },
    { "route": "Tabata Segerea - Bonyokwa", "fare": "700" },
    { "route": "Kinyerezi - Tabata Segerea", "fare": "700" },
    { "route": "Tabata Segerea - Kinyerezi", "fare": "700" },
    { "route": "Mnazi Mmoja - Tabata Segerea", "fare": "700" },
    { "route": "Tabata Segerea - Mnazi Mmoja", "fare": "700" },
    { "route": "Temeke/Tandika - Tabata Segerea", "fare": "700" },
    { "route": "Majumba Sita - Tabata Segerea", "fare": "700" },
    { "route": "Buguruni - Muhimbili", "fare": "700" },
    { "route": "Muhimbili - Buguruni", "fare": "700" },
    { "route": "Kariakoo - Temeke via Kilwa Road", "fare": "700" },
    { "route": "Buguruni - Mvuti", "fare": "700" },
    { "route": "Mvuti - Buguruni", "fare": "700" },
    { "route": "Temeke - Vingunguti", "fare": "700" },
    { "route": "Vingunguti - Temeke", "fare": "700" },
    { "route": "Buguruni - Yombo Vituka/Viwandani", "fare": "700" },
    { "route": "Yombo Vituka/Viwandani - Buguruni", "fare": "700" },
    { "route": "Buguruni Rozana - Ukonga Madafu", "fare": "700" },
    { "route": "Ukonga Madafu - Buguruni Rozana", "fare": "700" },
    { "route": "Mnazi Mmoja - Ukonga Madafu", "fare": "700" },
    { "route": "Ukonga Madafu - Mnazi Mmoja", "fare": "700" },
    { "route": "Kivukoni - Vingunguti", "fare": "700" },
    { "route": "Vingunguti - Kivukoni", "fare": "700" },
    { "route": "Muhimbili - Yombo Vituka", "fare": "700" },
    { "route": "Yombo Vituka - Muhimbili", "fare": "700" },
    { "route": "Banana - Kinyantira (Shule)", "fare": "700" },
    { "route": "Kinyantira (Shule) - Banana", "fare": "700" },
    { "route": "Buguruni - Chanika", "fare": "700" },
    { "route": "Chanika - Buguruni", "fare": "700" },
    { "route": "Buguruni - Gongo la Mboto", "fare": "700" },
    { "route": "Gongo la Mboto - Buguruni", "fare": "700" },
    { "route": "Chanika - Gongo la Mboto", "fare": "700" },
    { "route": "Gongo la Mboto - Chanika", "fare": "700" },
    { "route": "Gongo la Mboto - Kariakoo", "fare": "700" },
    { "route": "Kariakoo - Gongo la Mboto", "fare": "700" },
    { "route": "Gongo la Mboto - Kivukoni/Mnazi Mmoja", "fare": "700" },
    { "route": "Kivukoni/Mnazi Mmoja - Gongo la Mboto", "fare": "700" },
    { "route": "Banana - Kitunda", "fare": "700" },
    { "route": "Kitunda - Banana", "fare": "700" },
    { "route": "Banana - Kivule", "fare": "700" },
    { "route": "Kivule - Banana", "fare": "700" },
    { "route": "Banana - Machimbo", "fare": "700" },
    { "route": "Machimbo - Banana", "fare": "700" },
    { "route": "Kariakoo - Mabibo Mwisho Via Moro Rd", "fare": "700" },
    { "route": "Mabibo Mwisho - Kariakoo via Moro Rd", "fare": "700" },
    { "route": "Banana - Magole", "fare": "700" },
    { "route": "Magole - Banana", "fare": "700" },
    { "route": "Kariakoo - Machimbo", "fare": "700" },
    { "route": "Banana - Mwanagati", "fare": "700" },
    { "route": "Mwangati - Banana", "fare": "700" },
    { "route": "Banana/Mombasa - Kwa Moshi", "fare": "700" },
    { "route": "Kwa Moshi - Banana/Mombasa", "fare": "700" },
    { "route": "Machimbo - Kariakoo", "fare": "700" },
    { "route": "Mbezi Luis - Ubungo", "fare": "700" },
    { "route": "Ubungo - Mbezi Luis", "fare": "700" },
    { "route": "Makoka - Riverside (Ubungo)", "fare": "700" },
    { "route": "Riverside (Ubungo) - Makoka", "fare": "700" },
    { "route": "Ubungo - Buguruni", "fare": "700" },
    { "route": "Ubungo - Vingunguti", "fare": "700" },
    { "route": "Ubungo - Yombo Vituka", "fare": "700" },
    { "route": "Bonyokwa - Kimara Mwisho", "fare": "700" },
    { "route": "Kimara Mwisho - Bonyokwa", "fare": "700" },
    { "route": "Buguruni - Mbezi Luis (via Morogoro/Mandela Rd)", "fare": "700" },
    { "route": "Mbezi Luis - Buguruni (via Morogoro/Mandela Rd)", "fare": "700" },
    { "route": "Goba - Mbezi Luis", "fare": "700" },
    { "route": "Mbezi Luis - Goba", "fare": "700" },
    { "route": "Kigambioni-Pembamnazi/Buyuni", "fare": "700" },
    { "route": "Kibada - Kigamboni", "fare": "700" },
    { "route": "Kigamboni - Kibada", "fare": "700" },
    { "route": "Kibugumo - Kigamboni", "fare": "700" },
    { "route": "Kigamboni - Kibugumo", "fare": "700" },
    { "route": "Kigamboni - Kisiwani", "fare": "700" },
    { "route": "Kisiwani - Kigamboni", "fare": "700" },
    { "route": "Kigamboni - Ungindoni", "fare": "700" },
    { "route": "Ungindoni - Kigamboni", "fare": "700" },
    { "route": "Bunju - Kiwanda cha Dawa", "fare": "700" }
]
